Answer.py
Builder.py
DataPrinter.py
DataReader.py
PyQuest.py
Question.py
Validator.py
__init__.py
PyQuest_dnd-0.1.1.dist-info/LICENSE
PyQuest_dnd-0.1.1.dist-info/METADATA
PyQuest_dnd-0.1.1.dist-info/WHEEL
PyQuest_dnd-0.1.1.dist-info/top_level.txt
PyQuest_dnd-0.1.1.dist-info/RECORD
