Metadata-Version: 2.1
Name: PyQuest-dnd
Version: 0.1.1
Summary: A question and answer plaform that supports multiple(WIP!) terminal Q&A interactions and navigation. 
Author-email: CauseImCloudy <carter.loyd@causeimcloudy.dev>
License:                   GNU LESSER GENERAL PUBLIC LICENSE
Project-URL: Homepage, https://github.com/causeImCloudy/PyQuest
Project-URL: Issues, https://github.com/causeImCloudy/PyQuest/issues
Classifier: Programming Language :: Python :: 3
Classifier: License :: OSI Approved :: MIT License
Classifier: Operating System :: OS Independent
Requires-Python: >=3.12
License-File: LICENSE
